mp4upload/__init__.py
mp4upload/__meta__.py
mp4upload/__version__.py
mp4upload/downloader.py
mp4upload/downloader2.py
mp4upload/mp4upload.ini
mp4upload/mp4upload.py
mp4upload-0.2.5.dist-info/METADATA
mp4upload-0.2.5.dist-info/WHEEL
mp4upload-0.2.5.dist-info/entry_points.txt
mp4upload-0.2.5.dist-info/top_level.txt
mp4upload-0.2.5.dist-info/RECORD
