Metadata-Version: 2.4
Name: mp4upload
Version: 0.2.5
Summary: mp4upload url/link generator
Home-page: https://github.com/cumulus13/mp4upload
Author: Hadi Cahyadi LD
Author-email: cumulus13@gmail.com
Maintainer: cumulus13 Team
Maintainer-email: cumulus13@gmail.com
License: MIT
Project-URL: Documentation, https://github.com/cumulus13/mp4upload
Project-URL: Code, https://github.com/cumulus13/mp4upload
Classifier: Development Status :: 5 - Production/Stable
Classifier: Environment :: Console
Classifier: Intended Audience :: Developers
Classifier: License :: OSI Approved :: MIT License
Classifier: Operating System :: OS Independent
Classifier: Programming Language :: Python
Classifier: Programming Language :: Python :: 2
Classifier: Programming Language :: Python :: 3
Classifier: Topic :: Software Development :: Libraries :: Python Modules
Requires-Python: >=2.7
Requires-Dist: make_colors>=3.12
Requires-Dist: bs4
Requires-Dist: requests
Requires-Dist: configset
Requires-Dist: clipboard
Requires-Dist: pydebugger
Requires-Dist: xnotify
Requires-Dist: unidecode
Requires-Dist: bitmath
Requires-Dist: progress_session
Requires-Dist: licface
Requires-Dist: rich_argparse
Requires-Dist: rich
Dynamic: author
Dynamic: author-email
Dynamic: classifier
Dynamic: home-page
Dynamic: license
Dynamic: maintainer
Dynamic: maintainer-email
Dynamic: project-url
Dynamic: requires-dist
Dynamic: requires-python
Dynamic: summary
